LICENSE
MANIFEST.in
README.md
requirements.txt
setup.py
imagedirpreview/__init__.py
imagedirpreview/core.py
imagedirpreview/release.py
imagedirpreview.egg-info/PKG-INFO
imagedirpreview.egg-info/SOURCES.txt
imagedirpreview.egg-info/dependency_links.txt
imagedirpreview.egg-info/entry_points.txt
imagedirpreview.egg-info/requires.txt
imagedirpreview.egg-info/top_level.txt
imagedirpreview/templates/base.html