Metadata-Version: 1.0
Name: imagedirpreview
Version: 0.1.1
Summary: Script for previewing the image-content of directories on the file system
Home-page: https://github.com/cknoll/imagedirpreview
Author: Carsten Knoll
Author-email: UNKNOWN
License: BSD3
Keywords: image preview,helper script
Platform: UNKNOWN
